README.md
setup.cfg
setup.py
flamespeed/__init__.py
flamespeed/chemkin.py
flamespeed/parser.py
flamespeed/thermo.py
flamespeed.egg-info/PKG-INFO
flamespeed.egg-info/SOURCES.txt
flamespeed.egg-info/dependency_links.txt
flamespeed.egg-info/requires.txt
flamespeed.egg-info/top_level.txt
flamespeed/data/new_rxn_forms.xml
flamespeed/data/rxn_Duplicate.xml
flamespeed/data/rxn_ThreeBody.xml
flamespeed/data/rxn_TroeFalloffThreeBody.xml
flamespeed/data/rxns.xml
flamespeed/data/rxns_hw5.xml
flamespeed/data/rxns_irreversible.xml
flamespeed/data/rxns_mixed.xml
flamespeed/data/rxns_reversible.xml
flamespeed/data/rxns_reversible_ds.xml
flamespeed/data/rxns_reversible_mixed.xml
flamespeed/data/rxns_reversible_mod.xml
flamespeed/data/rxns_units.xml
flamespeed/data/rxns_units_test.xml
flamespeed/data/rxns_with_units.xml
flamespeed/data/thermo.sqlite
flamespeed/data/thermo_old.sqlite
flamespeed/data/tst.xml
flamespeed/data/units.csv
flamespeed/data/rxns_test/rxns_test_01.xml
flamespeed/data/rxns_test/rxns_test_02.xml
flamespeed/data/rxns_test/rxns_test_03.xml
flamespeed/data/rxns_test/rxns_test_04.xml
flamespeed/data/rxns_test/rxns_test_05.xml
flamespeed/data/rxns_test/rxns_test_06.xml
flamespeed/data/rxns_test/rxns_test_07.xml
flamespeed/data/rxns_test/rxns_test_08.xml
flamespeed/data/rxns_test/rxns_test_09.xml
flamespeed/data/rxns_test/rxns_test_10.xml
flamespeed/data/rxns_test/rxns_test_11.xml
flamespeed/data/rxns_test/rxns_test_12.xml
flamespeed/data/rxns_test/rxns_test_13.xml
flamespeed/data/rxns_test/rxns_test_14.xml
flamespeed/data/rxns_test/rxns_test_15.xml
flamespeed/data/rxns_test/rxns_test_16.xml
flamespeed/test/__init__.py
flamespeed/test/env.py
flamespeed/test/test_instance.py
flamespeed/test/test_reaction_coeffs.py
flamespeed/test/test_reaction_param.py
flamespeed/test/test_reaction_parser.py
flamespeed/test/test_reaction_rate.py