Metadata-Version: 1.2
Name: flamespeed
Version: 1.0.1
Summary: Chemical kinetics library for Python
Home-page: https://github.com/flamespeed/cs207-FinalProject/
Author: YTB
Author-email: student@g.harvard.edu
License: MIT
Platform: UNKNOWN
Requires-Python: >=3
